usdm4_pj/__info__.py
usdm4_pj/__init__.py
usdm4_pj/additional_attributes.py
usdm4_pj/data_file.py
usdm4_pj/expanded_view.py
usdm4_pj/procedure_costs.py
usdm4_pj/simple_view.py
usdm4_pj-0.3.0.dist-info/licenses/LICENSE
usdm4_pj-0.3.0.dist-info/METADATA
usdm4_pj-0.3.0.dist-info/WHEEL
usdm4_pj-0.3.0.dist-info/top_level.txt
usdm4_pj-0.3.0.dist-info/RECORD
